README.md
setup.py
rss_reader/__init__.py
rss_reader/cache.py
rss_reader/constants.py
rss_reader/executor.py
rss_reader/file_generator.py
rss_reader/verbosity.py
rss_reader_bektur.egg-info/PKG-INFO
rss_reader_bektur.egg-info/SOURCES.txt
rss_reader_bektur.egg-info/dependency_links.txt
rss_reader_bektur.egg-info/entry_points.txt
rss_reader_bektur.egg-info/requires.txt
rss_reader_bektur.egg-info/top_level.txt
tests/__init__.py
tests/rss_test.py